README.md
setup.cfg
setup.py
sparkworks/__init__.py
sparkworks/sparkworks.py
sparkworks.egg-info/PKG-INFO
sparkworks.egg-info/SOURCES.txt
sparkworks.egg-info/dependency_links.txt
sparkworks.egg-info/requires.txt
sparkworks.egg-info/top_level.txt