Metadata-Version: 1.1
Name: sparkworks
Version: 2.0.0
Summary: A client library for the sparkworks api
Home-page: http://sparkworks.net
Author: SparkWorks ITC
Author-email: info@sparkwokrs.net
License: UNKNOWN
Download-URL: https://github.com/SparkWorksnet/client
Keywords: client,sparkworks
Platform: UNKNOWN
